src/__init__.py
src/praxxis/__init__.py
src/praxxis/app.py
src/praxxis/display/__init__.py
src/praxxis/display/display_edit_ruleset.py
src/praxxis/display/display_error.py
src/praxxis/display/display_library.py
src/praxxis/display/display_model.py
src/praxxis/display/display_notebook.py
src/praxxis/display/display_param.py
src/praxxis/display/display_rulesengine.py
src/praxxis/display/display_scene.py
src/praxxis/display/display_settings.py
src/praxxis/entrypoints/__init__.py
src/praxxis/entrypoints/entry_library.py
src/praxxis/entrypoints/entry_model.py
src/praxxis/entrypoints/entry_notebook.py
src/praxxis/entrypoints/entry_parameter.py
src/praxxis/entrypoints/entry_rulesengine.py
src/praxxis/entrypoints/entry_scene.py
src/praxxis/entrypoints/entry_telemetry.py
src/praxxis/library/__init__.py
src/praxxis/library/add_library.py
src/praxxis/library/library.py
src/praxxis/library/list_library.py
src/praxxis/library/remove_library.py
src/praxxis/library/sync_library.py
src/praxxis/model/__init__.py
src/praxxis/model/import_model.py
src/praxxis/model/score.py
src/praxxis/model/update_model.py
src/praxxis/notebook/__init__.py
src/praxxis/notebook/add_notebook.py
src/praxxis/notebook/add_output.py
src/praxxis/notebook/list_notebook.py
src/praxxis/notebook/notebook.py
src/praxxis/notebook/open_notebook.py
src/praxxis/notebook/remove_notebook.py
src/praxxis/notebook/run_notebook.py
src/praxxis/notebook/search_notebook.py
src/praxxis/notebook/what_next.py
src/praxxis/parameter/__init__.py
src/praxxis/parameter/delete_param.py
src/praxxis/parameter/list_param.py
src/praxxis/parameter/pull_param.py
src/praxxis/parameter/set_param.py
src/praxxis/rulesengine/__init__.py
src/praxxis/rulesengine/activate_ruleset.py
src/praxxis/rulesengine/add_rule_to_ruleset.py
src/praxxis/rulesengine/deactivate_ruleset.py
src/praxxis/rulesengine/delete_rule_from_ruleset.py
src/praxxis/rulesengine/import_ruleset.py
src/praxxis/rulesengine/list_rulesets.py
src/praxxis/rulesengine/new_ruleset.py
praxxis-0.1.dev0.dist-info/LICENSE.md
praxxis-0.1.dev0.dist-info/METADATA
praxxis-0.1.dev0.dist-info/WHEEL
praxxis-0.1.dev0.dist-info/entry_points.txt
praxxis-0.1.dev0.dist-info/top_level.txt
praxxis-0.1.dev0.dist-info/RECORD
