Metadata-Version: 2.1
Name: praxxis
Version: 0.1.dev0
Summary: a notebook task interface built on big data and machine learning.
Home-page: https://github.com/microsoft/praxxis
Author: Skyler Clark, Amanda Bertsch, Swarathmika Kakivaya, Stuart Padley
Author-email: skylerjaneclark@gmail.com, abertsch72@gmail.com, swarathmika@hotmail.com
License: MIT
Platform: UNKNOWN
Classifier: Programming Language :: Python :: 3.7
Requires-Python: >=3.6.*
Requires-Dist: urllib3
Requires-Dist: requests
Requires-Dist: papermill
Requires-Dist: ijson
Requires-Dist: ipykernel
Requires-Dist: setuptools
Requires-Dist: nbopen
Requires-Dist: gitpython
Requires-Dist: toml
Requires-Dist: giturlparse
Requires-Dist: colorama
